Metadata-Version: 2.1
Name: huaweicloudstorepluginecs
Version: 0.0.4
Summary: Plugin that provides Huawei Cloud OBS Artifact Store functionality for MLflow
Home-page: https://github.com/adheeshagamage/huaweicloudstorepluginecs.git
Author: AKG103
Author-email: 
License: Apache License 2.0
License-File: LICENSE
